{
    "title":"详细页数据",
    "code":200,
    "data":[
        {
            "goodName":"自嗨锅1",
            "goodsId":"10010",
            "url":"10061.webp",
            "detail":"10017.jpg,10018.jpg,10019.jpg,10020.jpg,10021.jpg",
            "price":"79",
            "count":"200",
            "dic":"自嗨锅 川味麻辣烫自热火锅速食方便火锅143g/桶",
            "type":"广式腊肠煲仔饭，台式卤肉煲仔饭，牛肉煲仔饭",
            "weight":"0.3kg",
            "assess":"200+",
            "support":"可配送全球，99元免费基础运费,30质保",
            "buyCount":1
        },
        {
            "goodName":"自嗨锅2",
            "goodsId":"10011",
            "url":"10061.webp",
            "detail":"10018.jpg,10019.jpg,10020.jpg,10021.jpg,10017.jpg",
            "price":"79",
            "count":"200",
            "dic":"自嗨锅 川味麻辣烫自热火锅速食方便火锅143g/桶",
            "type":"广式腊肠煲仔饭，台式卤肉煲仔饭，牛肉煲仔饭",
            "weight":"0.3kg",
            "assess":"200+",
            "support":"可配送全球，99元免费基础运费,30质保",
            "buyCount":1
        },
        {
            "goodName":"自嗨锅3",
            "goodsId":"10012",
            "url":"10061.webp",
            "detail":"10019.jpg,10020.jpg,10021.jpg,10017.jpg,10018.jpg",
            "price":"79",
            "count":"200",
            "dic":"自嗨锅 川味麻辣烫自热火锅速食方便火锅143g/桶",
            "type":"广式腊肠煲仔饭，台式卤肉煲仔饭，牛肉煲仔饭",
            "weight":"0.3kg",
            "assess":"200+",
            "support":"可配送全球，99元免费基础运费,30质保",
            "buyCount":1
        },
        {
            "goodName":"自嗨锅4",
            "goodsId":"10013",
            "url":"10061.webp",
            "detail":"10020.jpg,10021.jpg,10017.jpg,10018.jpg,10019.jpg",
            "price":"79",
            "count":"200",
            "dic":"自嗨锅 川味麻辣烫自热火锅速食方便火锅143g/桶",
            "type":"广式腊肠煲仔饭，台式卤肉煲仔饭，牛肉煲仔饭",
            "weight":"0.3kg",
            "assess":"200+",
            "support":"可配送全球，99元免费基础运费,30质保",
            "buyCount":1
        },
        {
            "goodName":"自嗨锅5",
            "goodsId":"10014",
            "url":"10061.webp",
            "detail":"10021.jpg,10017.jpg,10018.jpg,10019.jpg,10020.jpg",
            "price":"79",
            "count":"200",
            "dic":"自嗨锅 川味麻辣烫自热火锅速食方便火锅143g/桶",
            "type":"广式腊肠煲仔饭，台式卤肉煲仔饭，牛肉煲仔饭",
            "weight":"0.3kg",
            "assess":"200+",
            "support":"可配送全球，99元免费基础运费,30质保",
            "buyCount":1
        }
    ]
}